pubmad/VERSION
pubmad/__init__.py
pubmad/pipeline.py
pubmad/types.py
pubmad/utils.py
pubmad/version.py
pubmad-1.0.1.dist-info/LICENSE.txt
pubmad-1.0.1.dist-info/METADATA
pubmad-1.0.1.dist-info/WHEEL
pubmad-1.0.1.dist-info/top_level.txt
pubmad-1.0.1.dist-info/RECORD
